{"tagline":"Tool shed to store environment setup and customizations","note":"Don't delete this file! It's used internally to help with page regeneration.","google":"","name":"Environments","body":"Ok so the idea here is to list out various environment setups and scripts incase of computer death as well as have somewhere to reference for improvements.\r\n\r\n## NPM Packages\r\n\r\n## Sublime Packages\r\n\r\n* FileDiffs\r\n\r\n## Sublime Settings\r\n\r\n```\r\n{\r\n# makes the sidebar a little easier to understand\r\n\"bold_folder_labels\": true,\r\n\r\n# looks cool :p\r\n\"caret_style\": \"phase\",\r\n\r\n# adds a subtle highlight to the current line\r\n\"highlight_line\": true,\r\n\r\n# in general this is good practice\r\n\"translate_tabs_to_spaces\": true,\r\n\r\n# trims trailing whitespace\r\n\"trim_trailing_white_space_on_save\": true,\r\n\r\n# I don't like to work at the very bottom of my screen\r\n\"scroll_past_end\": true,\r\n}\r\n```\r\n"}